{
  "string": [
    {
      "name": "module_desc",
      "value": "AgileDevHOS主工程"
    },
    {
      "name": "ability_desc",
      "value": "AgileDevHOS主Ability"
    },
    {
      "name": "internet_permission_reason",
      "value": "用于网络访问"
    },
    {
      "name": "imagevideo_permission_reason",
      "value": "用于访问媒体库资源"
    },
    {
      "name": "camera_permission_reason",
      "value": "用于使用相机"
    },
    {
      "name": "splash_title",
      "value": "AgileDevHOS测试工程"
    },
    {
      "name": "main_title",
      "value": "功能模块"
    },
    {
      "name": "main_change_mood",
      "value": "换个心情"
    },
    {
      "name": "preferences_title",
      "value": "Preferences测试类"
    },
    {
      "name": "preferences_input_hint",
      "value": "请输入要保存的文字"
    },
    {
      "name": "preferences_no_data",
      "value": "无数据"
    },
    {
      "name": "preferences_clear_log",
      "value": "清空日志"
    },
    {
      "name": "preferences_save_title",
      "value": "保存信息"
    },
    {
      "name": "preferences_save",
      "value": "保存"
    },
    {
      "name": "preferences_read",
      "value": "读取"
    },
    {
      "name": "preferences_get_all",
      "value": "获取全部"
    },
    {
      "name": "preferences_clean",
      "value": "清空所有"
    },
    {
      "name": "preferences_delete",
      "value": "删除数据"
    },
    {
      "name": "preferences_has",
      "value": "是否有数据"
    },
    {
      "name": "preferences_change_on",
      "value": "开启全量订阅"
    },
    {
      "name": "preferences_change_off",
      "value": "关闭全量订阅"
    },
    {
      "name": "preferences_data_change_on",
      "value": "开启精确订阅"
    },
    {
      "name": "preferences_data_change_off",
      "value": "关闭精确订阅"
    },
    {
      "name": "json_title",
      "value": "Json转换测试"
    },
    {
      "name": "json_to_bean",
      "value": "转bean对象"
    },
    {
      "name": "json_to_bean_transformer",
      "value": "转bean时数据转换"
    },
    {
      "name": "json_to_json",
      "value": "转json字符串"
    },
    {
      "name": "json_to_json_filter",
      "value": "转json并过滤"
    },
    {
      "name": "json_to_json_transformer",
      "value": "转json时数据转换"
    },
    {
      "name": "json_to_json_form",
      "value": "转json时格式化"
    },
    {
      "name": "json_has",
      "value": "对象是否包含某字段"
    },
    {
      "name": "json_remove",
      "value": "对象里删除某字段"
    },
    {
      "name": "json_clean",
      "value": "清空日志"
    },
    {
      "name": "mvvm_title",
      "value": "Mvvm测试类"
    },
    {
      "name": "componentV2_title",
      "value": "ComponentV2测试类"
    },
    {
      "name": "componentV2_local",
      "value": "@Local注解使用"
    },
    {
      "name": "componentV2_observedV2",
      "value": "@ObservedV2注解使用"
    },
    {
      "name": "componentV2_param_require",
      "value": "@Param搭配@Require注解使用"
    },
    {
      "name": "componentV2_param_once",
      "value": "@Param搭配@Once注解使用"
    },
    {
      "name": "componentV2_param_event",
      "value": "@Param搭配@Event注解使用"
    },
    {
      "name": "componentV2_double_bind",
      "value": "双向绑定使用"
    },
    {
      "name": "componentV2_provider",
      "value": "@Provider注解使用"
    },
    {
      "name": "componentV2_computed",
      "value": "@Computed注解使用"
    },
    {
      "name": "promise_title",
      "value": "Promise测试类"
    },
    {
      "name": "promise_success_switch",
      "value": "请求成功"
    },
    {
      "name": "promise_request_normal",
      "value": "无加载框请求"
    },
    {
      "name": "promise_request_dialog",
      "value": "加载框请求"
    },
    {
      "name": "promise_request_get",
      "value": "get网络图片"
    },
    {
      "name": "promise_request_post",
      "value": "post接口数据"
    },
    {
      "name": "refresh_load_title",
      "value": "刷新/加载更多测试类"
    },
    {
      "name": "event_bus_title",
      "value": "EventBus测试类"
    },
    {
      "name": "event_bus_register",
      "value": "订阅"
    },
    {
      "name": "event_bus_register_once",
      "value": "单次订阅"
    },
    {
      "name": "event_bus_unregister",
      "value": "取消订阅"
    },
    {
      "name": "event_bus_post",
      "value": "发送"
    },
    {
      "name": "event_bus_clean_log",
      "value": "清空日志"
    },
    {
      "name": "event_bus_go_detail",
      "value": "跳转详情"
    },
    {
      "name": "event_bus_detail_title",
      "value": "EventBus测试详情类"
    }
  ]
}